data_collection/__init__.py
data_collection/conftest.py
report_builder/__init__.py
report_builder/main.py
reportzz_ai-0.1.15.dist-info/METADATA
reportzz_ai-0.1.15.dist-info/WHEEL
reportzz_ai-0.1.15.dist-info/entry_points.txt
reportzz_ai-0.1.15.dist-info/top_level.txt
reportzz_ai-0.1.15.dist-info/RECORD
