Metadata-Version: 2.1
Name: reportzz-ai
Version: 0.1.15
Summary: Reportzz is a Python project that is designed to generate reports.
Home-page: https://github.com/zzirakadze/reportzz
Author: Zura Zirakadze
Author-email: zirakadzez@gmail.com
License: MIT
Requires-Dist: pytest
Requires-Dist: Jinja2
